keystonemiddleware/__init__.py
keystonemiddleware/ec2_token.py
keystonemiddleware/exceptions.py
keystonemiddleware/external_oauth2_token.py
keystonemiddleware/fixture.py
keystonemiddleware/i18n.py
keystonemiddleware/oauth2_mtls_token.py
keystonemiddleware/oauth2_token.py
keystonemiddleware/opts.py
keystonemiddleware/s3_token.py
keystonemiddleware/_common/__init__.py
keystonemiddleware/_common/config.py
keystonemiddleware/audit/__init__.py
keystonemiddleware/audit/_api.py
keystonemiddleware/audit/_notifier.py
keystonemiddleware/auth_token/__init__.py
keystonemiddleware/auth_token/_auth.py
keystonemiddleware/auth_token/_base.py
keystonemiddleware/auth_token/_cache.py
keystonemiddleware/auth_token/_exceptions.py
keystonemiddleware/auth_token/_identity.py
keystonemiddleware/auth_token/_memcache_crypt.py
keystonemiddleware/auth_token/_opts.py
keystonemiddleware/auth_token/_request.py
keystonemiddleware/auth_token/_user_plugin.py
keystonemiddleware/echo/__init__.py
keystonemiddleware/echo/__main__.py
keystonemiddleware/echo/service.py
keystonemiddleware/locale/en_GB/LC_MESSAGES/keystonemiddleware.po
keystonemiddleware/locale/ko_KR/LC_MESSAGES/keystonemiddleware.po
keystonemiddleware/tests/__init__.py
keystonemiddleware/tests/unit/__init__.py
keystonemiddleware/tests/unit/client_fixtures.py
keystonemiddleware/tests/unit/test_access_rules.py
keystonemiddleware/tests/unit/test_ec2_token_middleware.py
keystonemiddleware/tests/unit/test_entry_points.py
keystonemiddleware/tests/unit/test_external_oauth2_token_middleware.py
keystonemiddleware/tests/unit/test_fixtures.py
keystonemiddleware/tests/unit/test_oauth2_mtls_token_middleware.py
keystonemiddleware/tests/unit/test_oauth2_token_middleware.py
keystonemiddleware/tests/unit/test_opts.py
keystonemiddleware/tests/unit/test_s3_token_middleware.py
keystonemiddleware/tests/unit/utils.py
keystonemiddleware/tests/unit/audit/__init__.py
keystonemiddleware/tests/unit/audit/base.py
keystonemiddleware/tests/unit/audit/test_audit_api.py
keystonemiddleware-11.0.0.dist-info/licenses/AUTHORS
keystonemiddleware-11.0.0.dist-info/licenses/LICENSE
keystonemiddleware-11.0.0.dist-info/METADATA
keystonemiddleware-11.0.0.dist-info/WHEEL
keystonemiddleware-11.0.0.dist-info/entry_points.txt
keystonemiddleware-11.0.0.dist-info/pbr.json
keystonemiddleware-11.0.0.dist-info/top_level.txt
keystonemiddleware-11.0.0.dist-info/RECORD
